CHANGES.txt
CONTRIBUTORS.txt
MANIFEST.in
README.txt
setup.py
collective/__init__.py
collective.pfg.silverpop.egg-info/PKG-INFO
collective.pfg.silverpop.egg-info/SOURCES.txt
collective.pfg.silverpop.egg-info/dependency_links.txt
collective.pfg.silverpop.egg-info/entry_points.txt
collective.pfg.silverpop.egg-info/namespace_packages.txt
collective.pfg.silverpop.egg-info/not-zip-safe
collective.pfg.silverpop.egg-info/paster_plugins.txt
collective.pfg.silverpop.egg-info/requires.txt
collective.pfg.silverpop.egg-info/top_level.txt
collective/pfg/__init__.py
collective/pfg/silverpop/CHANGELOG
collective/pfg/silverpop/README.txt
collective/pfg/silverpop/__init__.py
collective/pfg/silverpop/config.py
collective/pfg/silverpop/configure.zcml
collective/pfg/silverpop/utilities.py
collective/pfg/silverpop/browser/__init__.py
collective/pfg/silverpop/browser/configure.zcml
collective/pfg/silverpop/content/__init__.py
collective/pfg/silverpop/content/configure.zcml
collective/pfg/silverpop/content/formsilverpopadapter.py
collective/pfg/silverpop/interfaces/__init__.py
collective/pfg/silverpop/interfaces/formsilverpopadapter.py
collective/pfg/silverpop/profiles/default/factorytool.xml
collective/pfg/silverpop/profiles/default/metadata.xml
collective/pfg/silverpop/profiles/default/portlets.xml
collective/pfg/silverpop/profiles/default/propertiestool.xml
collective/pfg/silverpop/profiles/default/rolemap.xml
collective/pfg/silverpop/profiles/default/types.xml
collective/pfg/silverpop/profiles/default/workflows.xml
collective/pfg/silverpop/profiles/default/types/FormFolder.xml
collective/pfg/silverpop/profiles/default/types/FormSilverpopAdapter.xml
collective/pfg/silverpop/tests/__init__.py
collective/pfg/silverpop/tests/base.py
collective/pfg/silverpop/tests/test_doctest.py
collective/pfg/silverpop/tests/test_mapping.py
collective/pfg/silverpop/tests/test_silverpop.py
docs/INSTALL.txt
docs/LICENSE.GPL
docs/LICENSE.txt