Metadata-Version: 1.0
Name: collective.pfg.silverpop
Version: 0.5
Summary: Addon for PloneFormGen providing Silverpop integration
Home-page: https://svn.plone.org/svn/collective/collective.pfg.silverpop/tags/0.5
Author: Hans-Peter Locher
Author-email: hans-peter.locher@inquant.de
License: GPL
Keywords: Plone PloneFormGen Silverpop
Platform: UNKNOWN
Classifier: Framework :: Plone
Classifier: Intended Audience :: Developers
Classifier: Topic :: Software Development :: Libraries :: Python Modules
Classifier: License :: OSI Approved :: GNU General Public License (GPL)
